mescal/CPC.py
mescal/__init__.py
mescal/adapt_efficiency.py
mescal/caching.py
mescal/change_ecoinvent.py
mescal/contribution_analysis.py
mescal/database.py
mescal/decommission.py
mescal/double_counting.py
mescal/esm.py
mescal/esm_back_to_lca.py
mescal/filesystem_constants.py
mescal/generate_lcia_obj_ampl.py
mescal/impact_assessment.py
mescal/modify_inventory.py
mescal/normalization.py
mescal/plot.py
mescal/regionalization.py
mescal/utils.py
mescal/data/mapping_existing_products_to_CPC.json
mescal/data/mapping_new_products_to_CPC.csv
mescal/data/ecoinvent_change_reports/Change Report Annex v3.10 - v3.10.1.xlsx
mescal/data/ecoinvent_change_reports/Change Report Annex v3.8 - v3.9.xlsx
mescal/data/ecoinvent_change_reports/Change Report Annex v3.9 - v3.9.1.xlsx
mescal/data/ecoinvent_change_reports/Change Report Annex v3.9.1 - v3.10.xlsx
mescal-1.2.3.dist-info/licenses/LICENSE
mescal-1.2.3.dist-info/METADATA
mescal-1.2.3.dist-info/WHEEL
mescal-1.2.3.dist-info/top_level.txt
mescal-1.2.3.dist-info/RECORD
