Metadata-Version: 2.4
Name: mescal
Version: 1.2.3
Summary: Coupling Energy System Models with Life Cycle Assessment
Author-email: Matthieu Souttre <matthieu.souttre@polymtl.ca>
Maintainer-email: Matthieu Souttre <matthieu.souttre@polymtl.ca>
License-Expression: MIT
Project-URL: source, https://github.com/matthieu-str/mescal
Project-URL: homepage, https://github.com/matthieu-str/mescal
Project-URL: tracker, https://github.com/matthieu-str/mescal/issues
Classifier: Intended Audience :: Science/Research
Classifier: Development Status :: 4 - Beta
Classifier: Programming Language :: Python :: 3.10
Classifier: Programming Language :: Python :: 3.11
Classifier: Programming Language :: Python :: 3.12
Classifier: Natural Language :: English
Classifier: Operating System :: OS Independent
Classifier: Topic :: Scientific/Engineering
Requires-Python: >=3.10
License-File: LICENSE
Requires-Dist: wurst==0.4
Requires-Dist: pandas
Requires-Dist: brightway2
Requires-Dist: plotly
Provides-Extra: testing
Requires-Dist: mescal; extra == "testing"
Requires-Dist: pytest; extra == "testing"
Requires-Dist: pytest-cov; extra == "testing"
Requires-Dist: python-coveralls; extra == "testing"
Provides-Extra: dev
Requires-Dist: build; extra == "dev"
Requires-Dist: pre-commit; extra == "dev"
Requires-Dist: pylint; extra == "dev"
Requires-Dist: pytest; extra == "dev"
Requires-Dist: pytest-cov; extra == "dev"
Requires-Dist: pytest-randomly; extra == "dev"
Requires-Dist: setuptools; extra == "dev"
Dynamic: license-file
